textdata/__init__.py
textdata/attrs.py
textdata/core.py
textdata/eval.py
textdata/table.py
textdata/util.py
textdata/version.py
textdata-2.4.1.dist-info/DESCRIPTION.rst
textdata-2.4.1.dist-info/METADATA
textdata-2.4.1.dist-info/RECORD
textdata-2.4.1.dist-info/WHEEL
textdata-2.4.1.dist-info/metadata.json
textdata-2.4.1.dist-info/top_level.txt
